django_password_reset-2.0.dist-info/METADATA
django_password_reset-2.0.dist-info/RECORD
django_password_reset-2.0.dist-info/WHEEL
django_password_reset-2.0.dist-info/top_level.txt
password_reset/__init__.py
password_reset/forms.py
password_reset/signals.py
password_reset/urls.py
password_reset/views.py
password_reset/locale/de/LC_MESSAGES/django.mo
password_reset/locale/de/LC_MESSAGES/django.po
password_reset/locale/es/LC_MESSAGES/django.mo
password_reset/locale/es/LC_MESSAGES/django.po
password_reset/locale/fr/LC_MESSAGES/django.mo
password_reset/locale/fr/LC_MESSAGES/django.po
password_reset/locale/ka/LC_MESSAGES/django.mo
password_reset/locale/ka/LC_MESSAGES/django.po
password_reset/locale/nb/LC_MESSAGES/django.mo
password_reset/locale/nb/LC_MESSAGES/django.po
password_reset/locale/nl/LC_MESSAGES/django.mo
password_reset/locale/nl/LC_MESSAGES/django.po
password_reset/locale/pl/LC_MESSAGES/django.mo
password_reset/locale/pl/LC_MESSAGES/django.po
password_reset/locale/pt_BR/LC_MESSAGES/django.mo
password_reset/locale/pt_BR/LC_MESSAGES/django.po
password_reset/locale/ru/LC_MESSAGES/django.mo
password_reset/locale/ru/LC_MESSAGES/django.po
password_reset/locale/zh/LC_MESSAGES/django.mo
password_reset/locale/zh/LC_MESSAGES/django.po
password_reset/templates/password_reset/base.html
password_reset/templates/password_reset/recovery_done.html
password_reset/templates/password_reset/recovery_email.txt
password_reset/templates/password_reset/recovery_email_subject.txt
password_reset/templates/password_reset/recovery_form.html
password_reset/templates/password_reset/reset.html
password_reset/templates/password_reset/reset_sent.html
password_reset/tests/__init__.py
password_reset/tests/models.py
password_reset/tests/settings.py
password_reset/tests/tests.py
password_reset/tests/urls.py
password_reset/tests/views.py
