Metadata-Version: 1.1
Name: django-password-reset
Version: 2.0
Summary: Class-based views for password reset.
Home-page: https://github.com/brutasse/django-password-reset
Author: Bruno Renie
Author-email: bruno@renie.fr
License: BSD licence, see LICENSE file
Platform: UNKNOWN
Classifier: Development Status :: 4 - Beta
Classifier: Environment :: Web Environment
Classifier: Framework :: Django
Classifier: Framework :: Django :: 1.11
Classifier: Framework :: Django :: 2.0
Classifier: Framework :: Django :: 2.1
Classifier: Intended Audience :: Developers
Classifier: License :: OSI Approved :: BSD License
Classifier: Natural Language :: English
Classifier: Programming Language :: Python
Classifier: Programming Language :: Python :: 3
